valediction/__init__.py
valediction/convenience.py
valediction/exceptions.py
valediction/integrity.py
valediction/progress.py
valediction/support.py
valediction/data_types/__init__.py
valediction/data_types/data_type_helpers.py
valediction/data_types/data_types.py
valediction/data_types/type_inference.py
valediction/datasets/__init__.py
valediction/datasets/datasets.py
valediction/datasets/datasets_helpers.py
valediction/demo/DEMO - Data Dictionary.xlsx
valediction/demo/DEMOGRAPHICS.csv
valediction/demo/DIAGNOSES.csv
valediction/demo/LAB_TESTS.csv
valediction/demo/VITALS.csv
valediction/demo/__init__.py
valediction/demo/demo_dictionary.py
valediction/dictionary/__init__.py
valediction/dictionary/exporting.py
valediction/dictionary/exporting_helpers.py
valediction/dictionary/generation.py
valediction/dictionary/helpers.py
valediction/dictionary/importing.py
valediction/dictionary/integrity.py
valediction/dictionary/model.py
valediction/dictionary/template/PROJECT - Data Dictionary.xltx
valediction/io/__init__.py
valediction/io/csv_readers.py
valediction/validation/__init__.py
valediction/validation/helpers.py
valediction/validation/issues.py
valediction/validation/validation.py
valediction-1.2.0.dist-info/METADATA
valediction-1.2.0.dist-info/WHEEL
valediction-1.2.0.dist-info/RECORD
