Metadata-Version: 2.4
Name: valediction
Version: 1.2.0
Summary: Valediction is a convenience data validation package that allows generation, import, and constraint enforcement of user-defined data dictionaries against datasets.
Author-email: Cai Davis <Cai.Davis@uhs.nhs.uk>
Requires-Python: <4.0,>=3.11
Requires-Dist: certifi<2025,>=2024.2.2
Requires-Dist: mohawk<2,>=1.1.0
Requires-Dist: openpyxl<4,>=3.1.5
Requires-Dist: pandas<3,>=2.2.1
Requires-Dist: pydantic<3,>=2.11.4
Requires-Dist: requests<3,>=2.31.0
Requires-Dist: tabulate<0.10,>=0.9.0
Requires-Dist: tqdm>=4.67.1
Requires-Dist: xlsxwriter<4,>=3.2.3
